includes/__init__.py
includes/bot.py
includes/config.py
includes/filereader.py
includes/scan.py
includes/writefile.py
utils/__init__.py
utils/configure.py
utils/const.py
utils/helpers.py
xss_scanner-1.0.0.dist-info/METADATA
xss_scanner-1.0.0.dist-info/WHEEL
xss_scanner-1.0.0.dist-info/entry_points.txt
xss_scanner-1.0.0.dist-info/top_level.txt
xss_scanner-1.0.0.dist-info/RECORD
