Metadata-Version: 2.1
Name: xss-scanner
Version: 1.0.0
Summary: CVE-2023-29489: XSS Bug scanner for WebPentesters and Bugbounty Hunters
Classifier: Programming Language :: Python :: 3
Classifier: License :: OSI Approved :: MIT License
Classifier: Operating System :: OS Independent
Requires-Dist: click
Requires-Dist: pyyaml
Requires-Dist: requests
